owlt_mcp_server/__init__.py
owlt_mcp_server/myjson.json
owlt_mcp_server/server.py
owlt_mcp_server/tools/csv_tools.py
owlt_mcp_server/utils/trans_func.py
owlt_mcp_server/utils/txtext.py
owlt_mcp_server/utils/yd_func.py
owlt_mcp_server/utils/yddoc.py
owlt_mcp_server-0.2.9.dist-info/METADATA
owlt_mcp_server-0.2.9.dist-info/WHEEL
owlt_mcp_server-0.2.9.dist-info/entry_points.txt
owlt_mcp_server-0.2.9.dist-info/RECORD
