Metadata-Version: 2.4
Name: owlt-mcp-server
Version: 0.2.9
Summary: A translator named owlt mcp server powered by professional LLMs
Author-email: jay <googcheng@qq.com>
Requires-Python: >=3.11.8
Requires-Dist: deepl>=1.22.0
Requires-Dist: lara-sdk>=1.4.0
Requires-Dist: mcp[cli]>=1.10.1
Requires-Dist: openai>=1.93.0
Requires-Dist: tencentcloud-sdk-python-common>=3.0.1412
Requires-Dist: tencentcloud-sdk-python-tmt>=3.0.947
